mercury/__init__.py
mercury/exceptions.py
mercury/automata/__init__.py
mercury/automata/_deterministic_finite_automata.py
mercury/automata/_deterministic_finite_transducer.py
mercury/decorators/__init__.py
mercury/decorators/_delta_function.py
mercury/decorators/_output_function.py
mercury/operations/__init__.py
mercury/operations/sets.py
mercury/static/index.html
mercury/static/pyGold.svg
mercury/static/assets/index-B-8E5vXd.css
mercury/static/assets/index-BvhnqZlu.js
mercury/types/__init__.py
mercury/types/_delta_function.py
mercury/types/_state.py
mercury/web/__init__.py
mercury/web/_dfa/dfa_schema.py
mercury/web/_dfa/dfa_view.py
mercury_lib-0.1.5.dist-info/licenses/LICENSE.txt
mercury_lib-0.1.5.dist-info/METADATA
mercury_lib-0.1.5.dist-info/WHEEL
mercury_lib-0.1.5.dist-info/top_level.txt
mercury_lib-0.1.5.dist-info/RECORD
