Metadata-Version: 2.4
Name: mercury-lib
Version: 0.1.5
Summary: Wrapper over `automata-lib` with the goal of supporting GOLD-3 syntax for automata development for students
Home-page: https://github.com/pyscaffold/pyscaffold/
Author: Nicolas-Saavedra
Author-email: personal@nicolassaavedra.com
License: Apache-2.0
Project-URL: Source, https://github.com/Nicolas-Saavedra/mercury-lib
Project-URL: Changelog, https://github.com/Nicolas-Saavedra/mercury-lib/blob/main/CHANGELOG.rst
Project-URL: Tracker, https://github.com/Nicolas-Saavedra/mercury-lib/issues
Platform: any
Classifier: Development Status :: 4 - Beta
Classifier: Programming Language :: Python
Requires-Python: >=3.12
License-File: LICENSE.txt
Requires-Dist: importlib-metadata; python_version < "3.8"
Requires-Dist: automata-lib>=9.0.0
Requires-Dist: uvicorn>=0.34.0
Provides-Extra: graphviz
Requires-Dist: pygraphviz>=1.10; extra == "graphviz"
Requires-Dist: coloraide>=1.8.2; extra == "graphviz"
Provides-Extra: web
Requires-Dist: fastapi>=0.115.8; extra == "web"
Provides-Extra: all
Requires-Dist: pygraphviz>=1.10; extra == "all"
Requires-Dist: coloraide>=1.8.2; extra == "all"
Requires-Dist: fastapi>=0.115.8; extra == "all"
Provides-Extra: testing
Requires-Dist: setuptools; extra == "testing"
Requires-Dist: pytest; extra == "testing"
Requires-Dist: pytest-cov; extra == "testing"
Dynamic: license-file
